sumt.py
sumt-3.12.3.dist-info/licenses/LICENSE
sumt-3.12.3.dist-info/METADATA
sumt-3.12.3.dist-info/WHEEL
sumt-3.12.3.dist-info/entry_points.txt
sumt-3.12.3.dist-info/top_level.txt
sumt-3.12.3.dist-info/RECORD
