Metadata-Version: 2.4
Name: sumt
Version: 3.12.3
Summary: Computes consensus trees and other phylogenetic tree summaries
Home-page: https://github.com/agormp/sumt
Author: Anders Gorm Pedersen
Author-email: agpe@dtu.dk
Classifier: Programming Language :: Python :: 3
Classifier: License :: OSI Approved :: GNU General Public License v3 (GPLv3)
Classifier: Operating System :: OS Independent
Requires-Python: >=3.6
License-File: LICENSE
Requires-Dist: phylotreelib==1.32.1
Requires-Dist: psutil
Dynamic: license-file
